{
  "title": "Affective Territories, Alternate Belonging",
  "parentCategory": "Exhibition",
  "categories": [
    "Art"
  ],
  "date": "2025-08-12T07:00:00.000Z",
  "heroImage": "https://scontent-sea1-1.cdninstagram.com/v/t51.29350-15/448536660_3657583274495473_2412911897942502053_n.jpg?stp=c288.0.864.864a_dst-jpg_e35_s640x640_tt6&_nc_cat=102&ccb=1-7&_nc_sid=18de74&_nc_ohc=YNpK2FEIwtEQ7kNvgEpLlta&_nc_oc=AdhmrceqBGACyiPeNXznySwmSeoQdlIKO6NAmbABX0YHQioF5NTBtE1JJFlJNd091pU&_nc_zt=23&_nc_ht=scontent-sea1-1.cdninstagram.com&_nc_gid=A70tNJ5rJhOlYQLSqJPf5xn&oh=00_AYFF48xLiDJLWasxXjRxhQQgOOd-ZhMCp34DCrKvIPVRTg&oe=67D8577D",
  "media": [
    "https://scontent-sea1-1.cdninstagram.com/v/t51.29350-15/448536660_3657583274495473_2412911897942502053_n.jpg?stp=c288.0.864.864a_dst-jpg_e35_s640x640_tt6&_nc_cat=102&ccb=1-7&_nc_sid=18de74&_nc_ohc=YNpK2FEIwtEQ7kNvgEpLlta&_nc_oc=AdhmrceqBGACyiPeNXznySwmSeoQdlIKO6NAmbABX0YHQioF5NTBtE1JJFlJNd091pU&_nc_zt=23&_nc_ht=scontent-sea1-1.cdninstagram.com&_nc_gid=A70tNJ5rJhOlYQLSqJPf5xn&oh=00_AYFF48xLiDJLWasxXjRxhQQgOOd-ZhMCp34DCrKvIPVRTg&oe=67D8577D"
  ],
  "link": "https://www.instagram.com/p/C8Upg9SJtO0/?hl=en&img_index=1",
  "ongoing": false,
  "forthcoming": true,
  "featured": false,
  "imageDescriptions": [],
  "isEvent": true
}